minnn/__init__.py
minnn/minnn.py
minnn/toolkit.py
minnn-0.0.2.dist-info/DESCRIPTION.rst
minnn-0.0.2.dist-info/METADATA
minnn-0.0.2.dist-info/RECORD
minnn-0.0.2.dist-info/WHEEL
minnn-0.0.2.dist-info/metadata.json
minnn-0.0.2.dist-info/top_level.txt
