Metadata-Version: 2.0
Name: minnn
Version: 0.0.2
Summary: Basic toolkit for neural networks
Home-page: UNKNOWN
Author: Wadood Abdul
Author-email: <wadood3003@gmail.com>
License: UNKNOWN
Keywords: python,neural networks,dnn,deep learning
Platform: UNKNOWN
Classifier: Development Status :: 1 - Planning
Classifier: Intended Audience :: Developers
Classifier: Programming Language :: Python :: 3
Classifier: Operating System :: Unix
Classifier: Operating System :: MacOS :: MacOS X
Classifier: Operating System :: Microsoft :: Windows
Requires-Dist: numpy
